<?xml version="1.0"?>
<!DOCTYPE hibernate-mapping PUBLIC "-//Hibernate/Hibernate Mapping DTD 3.0//EN"
"http://www.hibernate.org/dtd/hibernate-mapping-3.0.dtd">
<!-- Generated 20/11/2013 11:00:26 by Hibernate Tools 4.0.0 -->
<hibernate-mapping>
    <class name="org.freedom.persist.entity.Sgobjeto" table="SGOBJETO">
        <composite-id name="id" class="org.freedom.persist.entity.SgobjetoId">
            <key-property name="idobj" type="string">
                <column name="IDOBJ" length="30" />
            </key-property>
            <key-property name="codemp" type="int">
                <column name="CODEMP" />
            </key-property>
        </composite-id>
        <many-to-one name="sgempresa" class="org.freedom.persist.entity.Sgempresa" update="false" insert="false" fetch="select">
            <column name="CODEMP" not-null="true" />
        </many-to-one>
        <property name="descobj" type="string">
            <column name="DESCOBJ" length="50" not-null="true" />
        </property>
        <property name="tipoobj" type="string">
            <column name="TIPOOBJ" length="2" not-null="true" />
        </property>
        <property name="comentobj" type="string">
            <column name="COMENTOBJ" length="10000" />
        </property>
        <property name="usomeobj" type="java.lang.Character">
            <column name="USOMEOBJ" length="1" />
        </property>
        <property name="siglaobj" type="string">
            <column name="SIGLAOBJ" length="8" />
        </property>
        <property name="nivelobj" type="short">
            <column name="NIVELOBJ" not-null="true" />
        </property>
        <property name="numregobj" type="int">
            <column name="NUMREGOBJ" not-null="true" />
        </property>
        <property name="dtins" type="date">
            <column name="DTINS" length="10" not-null="true" />
        </property>
        <property name="hins" type="time">
            <column name="HINS" length="8" not-null="true" />
        </property>
        <property name="idusuins" type="string">
            <column name="IDUSUINS" length="8" not-null="true" />
        </property>
        <property name="dtalt" type="date">
            <column name="DTALT" length="10" />
        </property>
        <property name="halt" type="time">
            <column name="HALT" length="8" />
        </property>
        <property name="idusualt" type="string">
            <column name="IDUSUALT" length="8" />
        </property>
        <set name="sgobjetotbs" table="SGOBJETOTB" inverse="true" lazy="true" fetch="select">
            <key>
                <column name="IDOBJ" length="30" not-null="true" />
                <column name="CODEMP" not-null="true" />
            </key>
            <one-to-many class="org.freedom.persist.entity.Sgobjetotb" />
        </set>
        <set name="sgmenuobjs" table="SGMENUOBJ" inverse="true" lazy="true" fetch="select">
            <key>
                <column name="IDOBJ" length="30" not-null="true" />
                <column name="CODEMP" not-null="true" />
            </key>
            <one-to-many class="org.freedom.persist.entity.Sgmenuobj" />
        </set>
    </class>
</hibernate-mapping>
